{"cameraMode":{"drawMode":0,"name":"Shaded","section":"Shading Mode"},"sceneLighting":true,"audioPlay":false,"sceneViewState":{"m_AlwaysRefresh":false,"showFog":true,"showSkybox":true,"showFlares":true,"showImageEffects":true,"showParticleSystems":true,"showVisualEffectGraphs":true,"m_FxEnabled":false},"in2DMode":false,"pivot":{"x":550.0,"y":2.0,"z":570.0},"rotation":{"x":0.687752366065979,"y":-0.0032667152117937805,"z":0.0030949071515351536,"w":0.7259315252304077},"size":123.21439361572266,"orthographic":true}